{"@context":{"edi3":"https://edi3.org/vocabulary#","locodes-FK":"https://unece.org/codelists/locode#","rdf":"http://www.w3.org/1999/02/22-rdf-syntax-ns#","rdfs":"http://www.w3.org/2000/01/rdf-schema#"},"@graph":[{"@id":"locodes-FK:FK","@type":"edi3:UNECELOCODECountry","rdfs:comment":"FALKLAND ISLANDS (MALVINAS)","rdf:value":"FK"},{"@id":"locodes-FK:FKFBE","@type":"edi3:UNECELOCODE","edi3:country":"FK","rdfs:comment":"Fox Bay","rdf:value":"FKFBE"},{"@id":"locodes-FK:FKMPN","@type":"edi3:UNECELOCODE","edi3:country":"FK","rdfs:comment":"Mount Pleasant","rdf:value":"FKMPN"},{"@id":"locodes-FK:FKPSY","@type":"edi3:UNECELOCODE","edi3:country":"FK","rdfs:comment":"Port Stanley","rdf:value":"FKPSY"},{"@id":"locodes-FK:FKPWI","@type":"edi3:UNECELOCODE","edi3:country":"FK","rdfs:comment":"Port William","rdf:value":"FKPWI"}]}