{"@context":{"unece":"https://unece.org/vocab#","uncl7007":"https://unece.org/codelists/uncl7007#","rdf":"http://www.w3.org/1999/02/22-rdf-syntax-ns#","rdfs":"http://www.w3.org/2000/01/rdf-schema#"},"@graph":[{"@id":"uncl7007:Split","@type":"unece:UNECECL7007Code","rdfs:comment":"Separated into multiple units.","rdf:value":"1"},{"@id":"uncl7007:Missing","@type":"unece:UNECECL7007Code","rdfs:comment":"Absent or lacking.","rdf:value":"2"},{"@id":"uncl7007:Wrong_identification","@type":"unece:UNECECL7007Code","rdfs:comment":"The actual identification is different from the given identification.","rdf:value":"3"},{"@id":"uncl7007:Damaged","@type":"unece:UNECECL7007Code","rdfs:comment":"In a damaged state.","rdf:value":"4"},{"@id":"uncl7007:Good_condition","@type":"unece:UNECECL7007Code","rdfs:comment":"In a state of good condition.","rdf:value":"5"},{"@id":"uncl7007:Wrong_product","@type":"unece:UNECECL7007Code","rdfs:comment":"The product is wrong.","rdf:value":"6"},{"@id":"uncl7007:On_hold","@type":"unece:UNECECL7007Code","rdfs:comment":"Held, awaiting further action.","rdf:value":"7"},{"@id":"uncl7007:Proposed","@type":"unece:UNECECL7007Code","rdfs:comment":"The object is in a proposed state.","rdf:value":"8"},{"@id":"uncl7007:Accepted","@type":"unece:UNECECL7007Code","rdfs:comment":"The object is in an accepted state.","rdf:value":"9"},{"@id":"uncl7007:Scheduled","@type":"unece:UNECECL7007Code","rdfs:comment":"The object is in a scheduled state.","rdf:value":"10"},{"@id":"uncl7007:Completed","@type":"unece:UNECECL7007Code","rdfs:comment":"The object is in a completed state.","rdf:value":"11"},{"@id":"uncl7007:Rejected","@type":"unece:UNECECL7007Code","rdfs:comment":"The object is in a rejected state.","rdf:value":"12"},{"@id":"uncl7007:Postponed","@type":"unece:UNECECL7007Code","rdfs:comment":"The object is in a postponed state.","rdf:value":"13"},{"@id":"uncl7007:Cancelled","@type":"unece:UNECECL7007Code","rdfs:comment":"The object is in a cancelled state.","rdf:value":"14"},{"@id":"uncl7007:Obsolete","@type":"unece:UNECECL7007Code","rdfs:comment":"The object is obsolete.","rdf:value":"15"},{"@id":"uncl7007:Fresh","@type":"unece:UNECECL7007Code","rdfs:comment":"Retaining the original properties, not impaired by spoilage or preservation.","rdf:value":"16"},{"@id":"uncl7007:Defective","@type":"unece:UNECECL7007Code","rdfs:comment":"The object is defective or faulty.","rdf:value":"17"},{"@id":"uncl7007:Solid","@type":"unece:UNECECL7007Code","rdfs:comment":"A substance in the fundamental state of matter that retains its size and shape without need of a container.","rdf:value":"18"},{"@id":"uncl7007:Gas","@type":"unece:UNECECL7007Code","rdfs:comment":"Matter in a state where it occupies whatever volume is available.","rdf:value":"19"},{"@id":"uncl7007:Liquid","@type":"unece:UNECECL7007Code","rdfs:comment":"Matter in a state where it maintains a fixed volume but adapts to the shape of its container.","rdf:value":"20"},{"@id":"uncl7007:Return_goods","@type":"unece:UNECECL7007Code","rdfs:comment":"Identified goods are to be returned according to specified conditions.","rdf:value":"21"},{"@id":"uncl7007:Dispose_of_goods","@type":"unece:UNECECL7007Code","rdfs:comment":"The identified goods are to be disposed of.","rdf:value":"22"},{"@id":"uncl7007:Destroy_goods","@type":"unece:UNECECL7007Code","rdfs:comment":"The identified goods are to be destroyed.","rdf:value":"23"},{"@id":"uncl7007:Repair_goods","@type":"unece:UNECECL7007Code","rdfs:comment":"The identified goods are to be repaired.","rdf:value":"24"},{"@id":"uncl7007:Hold_for_examination","@type":"unece:UNECECL7007Code","rdfs:comment":"The identified goods are to be held for examination.","rdf:value":"25"},{"@id":"uncl7007:Return_refused","@type":"unece:UNECECL7007Code","rdfs:comment":"The return of the identified goods has been refused.","rdf:value":"26"},{"@id":"uncl7007:Product_safety_alert","@type":"unece:UNECECL7007Code","rdfs:comment":"The product is affected by a safety alert.","rdf:value":"27"}]}