{"@context":{"uncefact":"https://service.unece.org/trade/uncefact/vocabulary/uncefact#","unlocode-kw":"https://service.unece.org/trade/uncefact/vocabulary/unlocode-kw#","rdf":"http://www.w3.org/1999/02/22-rdf-syntax-ns#","rdfs":"http://www.w3.org/2000/01/rdf-schema#"},"@graph":[{"@id":"unlocode-kw:KWHMD","@type":"uncefact:UNLOCODE","uncefact:country":"KW","rdfs:comment":"Ahmadi","rdf:value":"KWHMD","rdf:label":"Ahmadi"},{"@id":"unlocode-kw:KWAHJ","@type":"uncefact:UNLOCODE","uncefact:country":"KW","rdfs:comment":"Ahmed Al Jaber","rdf:value":"KWAHJ","rdf:label":"Ahmed Al Jaber"},{"@id":"unlocode-kw:KWABD","@type":"uncefact:UNLOCODE","uncefact:country":"KW","rdfs:comment":"Al 'Abdaliyah","rdf:value":"KWABD","rdf:label":"Al 'Abdaliyah"},{"@id":"unlocode-kw:KWALF","@type":"uncefact:UNLOCODE","uncefact:country":"KW","rdfs:comment":"Al Farwaniyah","rdf:value":"KWALF","rdf:label":"Al Farwaniyah"},{"@id":"unlocode-kw:KWWAF","@type":"uncefact:UNLOCODE","uncefact:country":"KW","rdfs:comment":"Al Wafrah","rdf:value":"KWWAF","rdf:label":"Al Wafrah"},{"@id":"unlocode-kw:KWAIS","@type":"uncefact:UNLOCODE","uncefact:country":"KW","rdfs:comment":"Ali al Salem AB","rdf:value":"KWAIS","rdf:label":"Ali al Salem AB"},{"@id":"unlocode-kw:KWSYA","@type":"uncefact:UNLOCODE","uncefact:country":"KW","rdfs:comment":"As Sabahiyah","rdf:value":"KWSYA","rdf:label":"As Sabahiyah"},{"@id":"unlocode-kw:KWSAL","@type":"uncefact:UNLOCODE","uncefact:country":"KW","rdfs:comment":"As Salimiyah","rdf:value":"KWSAL","rdf:label":"As Salimiyah"},{"@id":"unlocode-kw:KWKHT","@type":"uncefact:UNLOCODE","uncefact:country":"KW","rdfs:comment":"As Sulaybikhat","rdf:value":"KWKHT","rdf:label":"As Sulaybikhat"},{"@id":"unlocode-kw:KWHAW","@type":"uncefact:UNLOCODE","uncefact:country":"KW","rdfs:comment":"Awalli","rdf:value":"KWHAW","rdf:label":"Awalli"},{"@id":"unlocode-kw:KWCAJ","@type":"uncefact:UNLOCODE","uncefact:country":"KW","rdfs:comment":"Camp Arifjan","rdf:value":"KWCAJ","rdf:label":"Camp Arifjan"},{"@id":"unlocode-kw:KWCBG","@type":"uncefact:UNLOCODE","uncefact:country":"KW","rdfs:comment":"Camp Buehring","rdf:value":"KWCBG","rdf:label":"Camp Buehring"},{"@id":"unlocode-kw:KWDOH","@type":"uncefact:UNLOCODE","uncefact:country":"KW","rdfs:comment":"Doha","rdf:value":"KWDOH","rdf:label":"Doha"},{"@id":"unlocode-kw:KWFIN","@type":"uncefact:UNLOCODE","uncefact:country":"KW","rdfs:comment":"Fintas","rdf:value":"KWFIN","rdf:label":"Fintas"},{"@id":"unlocode-kw:KWHWI","@type":"uncefact:UNLOCODE","uncefact:country":"KW","rdfs:comment":"Hawalli","rdf:value":"KWHWI","rdf:label":"Hawalli"},{"@id":"unlocode-kw:KWJBD","@type":"uncefact:UNLOCODE","uncefact:country":"KW","rdfs:comment":"Jebel Dhana","rdf:value":"KWJBD","rdf:label":"Jebel Dhana"},{"@id":"unlocode-kw:KWKFZ","@type":"uncefact:UNLOCODE","uncefact:country":"KW","rdfs:comment":"Kaifan","rdf:value":"KWKFZ","rdf:label":"Kaifan"},{"@id":"unlocode-kw:KWKWM","@type":"uncefact:UNLOCODE","uncefact:country":"KW","rdfs:comment":"Khor al Mufatta","rdf:value":"KWKWM","rdf:label":"Khor al Mufatta"},{"@id":"unlocode-kw:KWKWI","@type":"uncefact:UNLOCODE","uncefact:country":"KW","rdfs:comment":"Kuwait","rdf:value":"KWKWI","rdf:label":"Kuwait"},{"@id":"unlocode-kw:KWMIB","@type":"uncefact:UNLOCODE","uncefact:country":"KW","rdfs:comment":"Mina' 'Abd Allah","rdf:value":"KWMIB","rdf:label":"Mina' 'Abd Allah"},{"@id":"unlocode-kw:KWMEA","@type":"uncefact:UNLOCODE","uncefact:country":"KW","rdfs:comment":"Mina' al Ahmadi","rdf:value":"KWMEA","rdf:label":"Mina' al Ahmadi"},{"@id":"unlocode-kw:KWMZR","@type":"uncefact:UNLOCODE","uncefact:country":"KW","rdfs:comment":"Mina Al Zour","rdf:value":"KWMZR","rdf:label":"Mina Al Zour"},{"@id":"unlocode-kw:KWMAM","@type":"uncefact:UNLOCODE","uncefact:country":"KW","rdfs:comment":"Mina Alo Manti","rdf:value":"KWMAM","rdf:label":"Mina Alo Manti"},{"@id":"unlocode-kw:KWMIS","@type":"uncefact:UNLOCODE","uncefact:country":"KW","rdfs:comment":"Mina Saud","rdf:value":"KWMIS","rdf:label":"Mina Saud"},{"@id":"unlocode-kw:KWALR","@type":"uncefact:UNLOCODE","uncefact:country":"KW","rdfs:comment":"Ra's al Ard","rdf:value":"KWALR","rdf:label":"Ra's al Ard"},{"@id":"unlocode-kw:KWRUM","@type":"uncefact:UNLOCODE","uncefact:country":"KW","rdfs:comment":"Rumaithiya","rdf:value":"KWRUM","rdf:label":"Rumaithiya"},{"@id":"unlocode-kw:KWSAF","@type":"uncefact:UNLOCODE","uncefact:country":"KW","rdfs:comment":"Safat","rdf:value":"KWSAF","rdf:label":"Safat"},{"@id":"unlocode-kw:KWSMY","@type":"uncefact:UNLOCODE","uncefact:country":"KW","rdfs:comment":"Salmiya","rdf:value":"KWSMY","rdf:label":"Salmiya"},{"@id":"unlocode-kw:KWSAA","@type":"uncefact:UNLOCODE","uncefact:country":"KW","rdfs:comment":"Shuaiba","rdf:value":"KWSAA","rdf:label":"Shuaiba"},{"@id":"unlocode-kw:KWSWK","@type":"uncefact:UNLOCODE","uncefact:country":"KW","rdfs:comment":"Shuwaikh","rdf:value":"KWSWK","rdf:label":"Shuwaikh"},{"@id":"unlocode-kw:KWSUL","@type":"uncefact:UNLOCODE","uncefact:country":"KW","rdfs:comment":"Sulaibiya","rdf:value":"KWSUL","rdf:label":"Sulaibiya"},{"rdfs:label":"KUWAIT","@id":"unlocode-kw:KW","@type":"uncefact:UNLOCODE","rdfs:comment":"KUWAIT","rdf:value":"KW"}]}